{
    "exif_signatures": {},
    "file_size": 93060,
    "pdfid_signatures": {},
    "pypdf_uris": [
        "http://getpdf.pw/book?res=123&isbn=9780809573240&kwd=The%20Limbo%20Files",
        "http://getpdf.pw/book?res=123&isbn=9780809573240&kwd=The%20Limbo%20Files",
        "https://files8.webydo.com/9589062/UploadedFiles/F059A47C-36C0-09A3-0F06-2850F5AC3C73.pdf",
        "https://static.s123-cdn-static-b.com/uploads/4660601/normal_61b1065c409c6.pdf",
        "https://uploads.strikinglycdn.com/files/bc64e543-a7d0-4ce6-8711-13bb2d62e9c2/episodic-urbanism-architecture-urban-design-the-rmit-urban-spaces-project-1996-2015-467.pdf"
    ],
    "regex_uris": [
        "http://getpdf.pw/book?res=123&isbn=9780809573240&kwd=The%20Limbo%20Files",
        "http://getpdf.pw/book?res=123&isbn=9780809573240&kwd=The%20Limbo%20Files",
        "https://files8.webydo.com/9589062/UploadedFiles/F059A47C-36C0-09A3-0F06-2850F5AC3C73.pdf",
        "https://static.s123-cdn-static-b.com/uploads/4660601/normal_61b1065c409c6.pdf",
        "https://uploads.strikinglycdn.com/files/bc64e543-a7d0-4ce6-8711-13bb2d62e9c2/episodic-urbanism-architecture-urban-design-the-rmit-urban-spaces-project-1996-2015-467.pdf"
    ],
    "regex_urls": [
        "http://getpdf.pw/book?res=123",
        "http://getpdf.pw/book?res=123",
        "https",
        "https",
        "https"
    ],
    "scripts": {
        "iframe": [],
        "urls": []
    },
    "static_properties": {
        "JBIG2Decode": "0",
        "XML_forms": "0",
        "acro_form": "0",
        "auto_action": "0",
        "colors": "0",
        "cross_reference_table": "1",
        "embedded_files": "0",
        "file_size": "93",
        "java_script": "0",
        "js": "0",
        "launch_action": "0",
        "object_end": "65",
        "object_start": "65",
        "object_streams": "0",
        "open_action": "0",
        "page_count": "5",
        "rich_media": "0",
        "start_cross_reference_table": "1",
        "stream_end": "12",
        "stream_start": "12",
        "trailer_dictionary": "1"
    },
    "yara_signatures": [
        "without_attachments",
        "without_images",
        "with_urls",
        "invalid_trailer_structure",
        "contentis_base64"
    ]
}