{
    "exif_signatures": {},
    "file_size": 201306,
    "pdfid_signatures": {},
    "pypdf_uris": [
        "http://tds.advtraff2014.ru/wp1?keyword=%D0%BC%D0%B0%D1%82%D0%B5%D1%80%D0%B8%D0%B0%D0%BB%D1%8B+%D0%B4%D0%BB%D1%8F+%D0%BF%D0%BE%D0%B4%D0%B3%D0%BE%D1%82%D0%BE%D0%B2%D0%BA%D0%B8+%D0%BA+%D0%B5%D0%B3%D1%8D+%D0%BF%D0%BE+%D0%B1%D0%B8%D0%BE%D0%BB%D0%BE%D0%B3%D0%B8%D0%B8+2018",
        "https://cilopajupexeqado.files.wordpress.com/2018/04/kijatirubatap-789-nomer-gdz-atanasian-natewumojixow.pdf",
        "https://polafaterirenide.files.wordpress.com/2018/04/fivowijabuj-reshebnik-po-matematike-2-klass-uchebnik-2-chast-moro-wiloxaz.pdf",
        "https://vugumafiq.files.wordpress.com/2018/04/bowufuxowu-ege-kakie-predmety-sdavat-nivegikag.pdf",
        "https://kigebomigimunopibuq.files.wordpress.com/2018/04/putoteb-gdz-russkii-iazyk-konovalova-7-2016-bujagadobe.pdf",
        "https://hinerebopip.files.wordpress.com/2018/04/zipam-reshebnik-obzh-smirnov-7-klass-xavepedux.pdf",
        "https://moveqebupidivawo.files.wordpress.com/2018/04/tikanavi-mordkovich-nikolaev-algebra-7-klass-zadachnik-1-chast-femem.pdf",
        "https://pawetegemecepoguqum.files.wordpress.com/2018/04/pazibetoniwaro-gdz-po-geografii-5-klass-tetrad-praktikum-kotliar-otvety-stranitsa-12-rolerevol.pdf",
        "https://kapojoweracojawulobe.files.wordpress.com/2018/04/weguwuwadudexo-reshebnik-8-klass-po-ukrainskomu-iazyku-zabolotnyi-bubar.pdf"
    ],
    "regex_uris": [
        "http://tds.advtraff2014.ru/wp1?keyword=%D0%BC%D0%B0%D1%82%D0%B5%D1%80%D0%B8%D0%B0%D0%BB%D1%8B+%D0%B4%D0%BB%D1%8F+%D0%BF%D0%BE%D0%B4%D0%B3%D0%BE%D1%82%D0%BE%D0%B2%D0%BA%D0%B8+%D0%BA+%D0%B5%D0%B3%D1%8D+%D0%BF%D0%BE+%D0%B1%D0%B8%D0%BE%D0%BB%D0%BE%D0%B3%D0%B8%D0%B8+2018",
        "https://cilopajupexeqado.files.wordpress.com/2018/04/kijatirubatap-789-nomer-gdz-atanasian-natewumojixow.pdf",
        "https://polafaterirenide.files.wordpress.com/2018/04/fivowijabuj-reshebnik-po-matematike-2-klass-uchebnik-2-chast-moro-wiloxaz.pdf",
        "https://vugumafiq.files.wordpress.com/2018/04/bowufuxowu-ege-kakie-predmety-sdavat-nivegikag.pdf",
        "https://kigebomigimunopibuq.files.wordpress.com/2018/04/putoteb-gdz-russkii-iazyk-konovalova-7-2016-bujagadobe.pdf",
        "https://hinerebopip.files.wordpress.com/2018/04/zipam-reshebnik-obzh-smirnov-7-klass-xavepedux.pdf",
        "https://moveqebupidivawo.files.wordpress.com/2018/04/tikanavi-mordkovich-nikolaev-algebra-7-klass-zadachnik-1-chast-femem.pdf",
        "https://pawetegemecepoguqum.files.wordpress.com/2018/04/pazibetoniwaro-gdz-po-geografii-5-klass-tetrad-praktikum-kotliar-otvety-stranitsa-12-rolerevol.pdf",
        "https://kapojoweracojawulobe.files.wordpress.com/2018/04/weguwuwadudexo-reshebnik-8-klass-po-ukrainskomu-iazyku-zabolotnyi-bubar.pdf"
    ],
    "regex_urls": [
        "http://tds.advtraff2014.ru/wp1?keyword=%D0%BC%D0%B0%D1%82%D0%B5%D1%80%D0%B8%D0%B0%D0%BB%D1%8B+%D0%B4%D0%BB%D1%8F+%D0%BF%D0%BE%D0%B4%D0%B3%D0%BE%D1%82%D0%BE%D0%B2%D0%BA%D0%B8+%D0%BA+%D0%B5%D0%B3%D1%8D+%D0%BF%D0%BE+%D0%B1%D0%B8%D0%BE%D0%BB%D0%BE%D0%B3%D0%B8%D0%B8+2018",
        "https",
        "https",
        "https",
        "https",
        "https",
        "https",
        "https",
        "https"
    ],
    "scripts": {
        "iframe": [],
        "urls": []
    },
    "static_properties": {
        "JBIG2Decode": "0",
        "XML_forms": "0",
        "acro_form": "0",
        "auto_action": "0",
        "colors": "0",
        "cross_reference_table": "1",
        "embedded_files": "0",
        "file_size": "201",
        "java_script": "0",
        "js": "0",
        "launch_action": "0",
        "object_end": "56",
        "object_start": "56",
        "object_streams": "0",
        "open_action": "0",
        "page_count": "4",
        "rich_media": "0",
        "start_cross_reference_table": "1",
        "stream_end": "11",
        "stream_start": "11",
        "trailer_dictionary": "1"
    },
    "yara_signatures": [
        "without_attachments",
        "without_images",
        "with_urls",
        "invalid_trailer_structure",
        "contentis_base64"
    ]
}