{
    "exif_signatures": {},
    "file_size": 93664,
    "pdfid_signatures": {},
    "pypdf_uris": [
        "https://botokaw.ru/strik?utm_term=maus+my+father+bleeds+history+chapter+summary",
        "http://vekamujibatebig.rf.gd/sawazenijuxuxitakazo.pdf",
        "http://lalemifeluruka.epizy.com/nofidupukelafogalim.pdf",
        "http://com-connexion.xyz/sugenela2tlsd.pdf",
        "https://cdn-cms.f-static.net/uploads/4472774/normal_60133f685b139.pdf",
        "http://kovuzaxaf.medianewsonline.com/double_bollinger_bands_trading_strategy.pdf",
        "https://static.s123-cdn-static.com/uploads/4381297/normal_5fccfd8dc9695.pdf",
        "http://xukosususif.medianewsonline.com/role_de_l_appareil_de_golgi.pdf",
        "http://freshmind.net/33680540519co1uc.pdf",
        "https://uploads.strikinglycdn.com/files/b63aa296-ee46-4c3f-85b9-4f64b24257bd/38143889733.pdf",
        "https://uploads.strikinglycdn.com/files/8568c068-7308-47a5-a5a3-14ba142c1915/sanyo_tv_review_mouthshut.pdf",
        "http://changepass.online/ukulele_strumming_patterns_4_4d4fg6.pdf",
        "http://muzizax.rf.gd/20558719619.pdf",
        "http://nefozufovi.scienceontheweb.net/aeneid_with_line_numbers.pdf",
        "http://zumepaposakuf.scienceontheweb.net/creative_writing_grade_12.pdf",
        "http://sberin.xyz/49064248099ja9e1.pdf",
        "http://viniwowosur.onlinewebshop.net/37981017848.pdf",
        "https://uploads.strikinglycdn.com/files/f99742b9-a1ee-48bd-9995-9aaba1241907/five_nights_at_freddys_costumes_for_halloween.pdf",
        "http://lidufaz.epizy.com/81621232830.pdf",
        "https://static.s123-cdn-static.com/uploads/4374366/normal_5fcbfca7d281d.pdf",
        "http://vafumukiwafi.iblogger.org/javamatojav.pdf"
    ],
    "regex_uris": [
        "https://botokaw.ru/strik?utm_term=maus+my+father+bleeds+history+chapter+summary",
        "http://vekamujibatebig.rf.gd/sawazenijuxuxitakazo.pdf",
        "http://lalemifeluruka.epizy.com/nofidupukelafogalim.pdf",
        "http://com-connexion.xyz/sugenela2tlsd.pdf",
        "https://cdn-cms.f-static.net/uploads/4472774/normal_60133f685b139.pdf",
        "http://kovuzaxaf.medianewsonline.com/double_bollinger_bands_trading_strategy.pdf",
        "https://static.s123-cdn-static.com/uploads/4381297/normal_5fccfd8dc9695.pdf",
        "http://xukosususif.medianewsonline.com/role_de_l_appareil_de_golgi.pdf",
        "http://freshmind.net/33680540519co1uc.pdf",
        "https://uploads.strikinglycdn.com/files/b63aa296-ee46-4c3f-85b9-4f64b24257bd/38143889733.pdf",
        "https://uploads.strikinglycdn.com/files/8568c068-7308-47a5-a5a3-14ba142c1915/sanyo_tv_review_mouthshut.pdf",
        "http://changepass.online/ukulele_strumming_patterns_4_4d4fg6.pdf",
        "http://muzizax.rf.gd/20558719619.pdf",
        "http://nefozufovi.scienceontheweb.net/aeneid_with_line_numbers.pdf",
        "http://zumepaposakuf.scienceontheweb.net/creative_writing_grade_12.pdf",
        "http://sberin.xyz/49064248099ja9e1.pdf",
        "http://viniwowosur.onlinewebshop.net/37981017848.pdf",
        "https://uploads.strikinglycdn.com/files/f99742b9-a1ee-48bd-9995-9aaba1241907/five_nights_at_freddys_costumes_for_halloween.pdf",
        "http://lidufaz.epizy.com/81621232830.pdf",
        "https://static.s123-cdn-static.com/uploads/4374366/normal_5fcbfca7d281d.pdf",
        "http://vafumukiwafi.iblogger.org/javamatojav.pdf"
    ],
    "regex_urls": [
        "https",
        "http://vekamujibatebig.rf.gd/sawazenijuxuxitakazo.pdf",
        "http://lalemifeluruka.epizy.com/nofidupukelafogalim.pdf",
        "http://com-connexion.xyz/sugenela2tlsd.pdf",
        "https",
        "http://kovuzaxaf.medianewsonline.com/double_bollinger_bands_trading_strategy.pdf",
        "https",
        "http://xukosususif.medianewsonline.com/role_de_l_appareil_de_golgi.pdf",
        "http://freshmind.net/33680540519co1uc.pdf",
        "https",
        "https",
        "http://changepass.online/ukulele_strumming_patterns_4_4d4fg6.pdf",
        "http://muzizax.rf.gd/20558719619.pdf",
        "http://nefozufovi.scienceontheweb.net/aeneid_with_line_numbers.pdf",
        "http://zumepaposakuf.scienceontheweb.net/creative_writing_grade_12.pdf",
        "http://sberin.xyz/49064248099ja9e1.pdf",
        "http://viniwowosur.onlinewebshop.net/37981017848.pdf",
        "https",
        "http://lidufaz.epizy.com/81621232830.pdf",
        "https",
        "http://vafumukiwafi.iblogger.org/javamatojav.pdf",
        "http://www.w3.org/1999/02/22-rdf-syntax-ns#",
        "http://purl.org/dc/elements/1.1/",
        "http://ns.adobe.com/pdf/1.3/",
        "http://ns.adobe.com/xap/1.0/",
        "http://ns.adobe.com/xap/1.0/mm/",
        "http://ns.adobe.com/xap/1.0/rights/"
    ],
    "scripts": {
        "iframe": [],
        "urls": []
    },
    "static_properties": {
        "JBIG2Decode": "0",
        "XML_forms": "0",
        "acro_form": "0",
        "auto_action": "0",
        "colors": "0",
        "cross_reference_table": "2",
        "embedded_files": "0",
        "file_size": "94",
        "java_script": "0",
        "js": "0",
        "launch_action": "0",
        "object_end": "57",
        "object_start": "57",
        "object_streams": "0",
        "open_action": "0",
        "page_count": "2",
        "rich_media": "0",
        "start_cross_reference_table": "2",
        "stream_end": "8",
        "stream_start": "8",
        "trailer_dictionary": "2"
    },
    "yara_signatures": [
        "without_attachments",
        "without_images",
        "with_urls",
        "invalid_trailer_structure",
        "multiple_versions",
        "contentis_base64",
        "Big_Numbers1"
    ]
}