{
    "exif_signatures": {},
    "file_size": 93939,
    "pdfid_signatures": {},
    "pypdf_uris": [
        "http://getpdf.pw/book?res=123&isbn=9781453796047&kwd=Eye%20Candy%20:%20New%20Images",
        "http://getpdf.pw/book?res=123&isbn=9781453796047&kwd=Eye%20Candy%20:%20New%20Images",
        "https://cdn-cms.f-static.net/uploads/4661044/normal_61af95dad01f0.pdf",
        "https://img1.wsimg.com/blobby/go/7fa436d4-7413-47aa-8602-d87c5555b4a1/the-cracking-tower-966.pdf"
    ],
    "regex_uris": [
        "http://getpdf.pw/book?res=123&isbn=9781453796047&kwd=Eye%20Candy%20:%20New%20Images",
        "http://getpdf.pw/book?res=123&isbn=9781453796047&kwd=Eye%20Candy%20:%20New%20Images",
        "https://cdn-cms.f-static.net/uploads/4661044/normal_61af95dad01f0.pdf",
        "https://img1.wsimg.com/blobby/go/7fa436d4-7413-47aa-8602-d87c5555b4a1/the-cracking-tower-966.pdf"
    ],
    "regex_urls": [
        "http://getpdf.pw/book?res=123",
        "http://getpdf.pw/book?res=123",
        "https",
        "https"
    ],
    "scripts": {
        "iframe": [],
        "urls": []
    },
    "static_properties": {
        "JBIG2Decode": "0",
        "XML_forms": "0",
        "acro_form": "0",
        "auto_action": "0",
        "colors": "0",
        "cross_reference_table": "1",
        "embedded_files": "0",
        "file_size": "94",
        "java_script": "0",
        "js": "0",
        "launch_action": "0",
        "object_end": "64",
        "object_start": "64",
        "object_streams": "0",
        "open_action": "0",
        "page_count": "5",
        "rich_media": "0",
        "start_cross_reference_table": "1",
        "stream_end": "12",
        "stream_start": "12",
        "trailer_dictionary": "1"
    },
    "yara_signatures": [
        "without_attachments",
        "without_images",
        "with_urls",
        "invalid_trailer_structure",
        "contentis_base64"
    ]
}