{
    "exif_signatures": {},
    "file_size": 74327,
    "pdfid_signatures": {},
    "pypdf_uris": [
        "https://maypoin.ru/strik?utm_term=mini+diccionario+visual+espa%25C3%25B1ol+ingles+larousse+pdf",
        "https://cdn-cms.f-static.net/uploads/4447086/normal_5fd174c777f9c.pdf",
        "https://s3.amazonaws.com/kefiperizonofu/wafitumi.pdf",
        "https://cdn-cms.f-static.net/uploads/4491665/normal_6023de8b34b13.pdf",
        "https://a35b4eae-300a-44a5-b982-8d633984e519.filesusr.com/ugd/19735e_d9cb1ba4535c441b8f1b0d590b4a4b42.pdf?index=true",
        "http://wajufuful.rf.gd/life_bookstore_kuching_sarawak.pdf",
        "https://voromelub.weebly.com/uploads/1/3/4/8/134872571/rukumokujete.pdf",
        "http://nufolupi.epizy.com/ardour_full_crack.pdf",
        "https://s3.amazonaws.com/damerirazib/68991533570.pdf",
        "http://pumesuj.iblogger.org/nizekewila.pdf",
        "https://static.s123-cdn-static.com/uploads/4426682/normal_5fe5404be8885.pdf",
        "https://static.s123-cdn-static.com/uploads/4422659/normal_60089926a926c.pdf",
        "https://ff06b2c9-6223-4357-b4d5-1bf3807c749f.filesusr.com/ugd/717131_8d7896e1da404e63ba297ef9e217b688.pdf?index=true",
        "https://static.s123-cdn-static.com/uploads/4390382/normal_6000fb5dbfe71.pdf",
        "https://sowozulame.weebly.com/uploads/1/3/4/7/134733070/645b1c48738c2.pdf",
        "https://static.s123-cdn-static.com/uploads/4465136/normal_5fec8fd40a36b.pdf",
        "http://wirajamosilun.22web.org/35396479446.pdf",
        "https://static.s123-cdn-static.com/uploads/4467561/normal_5feeb32ad2031.pdf",
        "https://32b33340-d9da-4ef7-b3bd-a0ac5134eb71.filesusr.com/ugd/adfa6f_f42d56d4e1c6467eb5cfd687ce8cab7d.pdf?index=true",
        "https://s3.amazonaws.com/tojazudibumogab/charles_darwin_school_norwich_uniform.pdf",
        "https://nisivijuwowog.weebly.com/uploads/1/3/0/8/130813757/7c81c6daa63e.pdf"
    ],
    "regex_uris": [
        "https://maypoin.ru/strik?utm_term=mini+diccionario+visual+espa%25C3%25B1ol+ingles+larousse+pdf",
        "https://cdn-cms.f-static.net/uploads/4447086/normal_5fd174c777f9c.pdf",
        "https://s3.amazonaws.com/kefiperizonofu/wafitumi.pdf",
        "https://cdn-cms.f-static.net/uploads/4491665/normal_6023de8b34b13.pdf",
        "https://a35b4eae-300a-44a5-b982-8d633984e519.filesusr.com/ugd/19735e_d9cb1ba4535c441b8f1b0d590b4a4b42.pdf?index=true",
        "http://wajufuful.rf.gd/life_bookstore_kuching_sarawak.pdf",
        "https://voromelub.weebly.com/uploads/1/3/4/8/134872571/rukumokujete.pdf",
        "http://nufolupi.epizy.com/ardour_full_crack.pdf",
        "https://s3.amazonaws.com/damerirazib/68991533570.pdf",
        "http://pumesuj.iblogger.org/nizekewila.pdf",
        "https://static.s123-cdn-static.com/uploads/4426682/normal_5fe5404be8885.pdf",
        "https://static.s123-cdn-static.com/uploads/4422659/normal_60089926a926c.pdf",
        "https://ff06b2c9-6223-4357-b4d5-1bf3807c749f.filesusr.com/ugd/717131_8d7896e1da404e63ba297ef9e217b688.pdf?index=true",
        "https://static.s123-cdn-static.com/uploads/4390382/normal_6000fb5dbfe71.pdf",
        "https://sowozulame.weebly.com/uploads/1/3/4/7/134733070/645b1c48738c2.pdf",
        "https://static.s123-cdn-static.com/uploads/4465136/normal_5fec8fd40a36b.pdf",
        "http://wirajamosilun.22web.org/35396479446.pdf",
        "https://static.s123-cdn-static.com/uploads/4467561/normal_5feeb32ad2031.pdf",
        "https://32b33340-d9da-4ef7-b3bd-a0ac5134eb71.filesusr.com/ugd/adfa6f_f42d56d4e1c6467eb5cfd687ce8cab7d.pdf?index=true",
        "https://s3.amazonaws.com/tojazudibumogab/charles_darwin_school_norwich_uniform.pdf",
        "https://nisivijuwowog.weebly.com/uploads/1/3/0/8/130813757/7c81c6daa63e.pdf"
    ],
    "regex_urls": [
        "https",
        "https",
        "https",
        "https",
        "https",
        "http://wajufuful.rf.gd/life_bookstore_kuching_sarawak.pdf",
        "https",
        "http://nufolupi.epizy.com/ardour_full_crack.pdf",
        "https",
        "http://pumesuj.iblogger.org/nizekewila.pdf",
        "https",
        "https",
        "https",
        "https",
        "https",
        "https",
        "http://wirajamosilun.22web.org/35396479446.pdf",
        "https",
        "https",
        "https",
        "https",
        "http://www.w3.org/1999/02/22-rdf-syntax-ns#",
        "http://purl.org/dc/elements/1.1/",
        "http://librosdejoe.b",
        "http://librosdejoe.b",
        "http://ns.adobe.com/pdf/1.3/",
        "http://ns.adobe.com/xap/1.0/",
        "http://ns.adobe.com/xap/1.0/mm/",
        "http://ns.adobe.com/xap/1.0/rights/"
    ],
    "scripts": {
        "iframe": [],
        "urls": []
    },
    "static_properties": {
        "JBIG2Decode": "0",
        "XML_forms": "0",
        "acro_form": "0",
        "auto_action": "0",
        "colors": "0",
        "cross_reference_table": "2",
        "embedded_files": "0",
        "file_size": "74",
        "java_script": "0",
        "js": "0",
        "launch_action": "0",
        "object_end": "57",
        "object_start": "57",
        "object_streams": "0",
        "open_action": "0",
        "page_count": "2",
        "rich_media": "0",
        "start_cross_reference_table": "2",
        "stream_end": "8",
        "stream_start": "8",
        "trailer_dictionary": "2"
    },
    "yara_signatures": [
        "suspicious_packer_section",
        "without_attachments",
        "without_images",
        "with_urls",
        "invalid_trailer_structure",
        "multiple_versions",
        "contentis_base64",
        "Big_Numbers1",
        "Big_Numbers2"
    ]
}