{
    "exif_signatures": {
        "linearized": {
            "description": "This PDF is linearized",
            "families": [],
            "marks": [],
            "name": "linearized",
            "references": [],
            "severity": 1
        }
    },
    "file_size": 3344211,
    "pdfid_signatures": {},
    "pypdf_uris": [
        "https://webfoundation.org",
        "https://www.feministinternet.com",
        "https://craigwalker.com.au",
        "https://contractfortheweb.org/",
        "https://forum.generationequality.org/sites/default/files/2021-03/TIGE_FINAL_VISUAL_EN.pdf",
        "https://forum.generationequality.org/sites/default/files/2021-03/TIGE_FINAL_VISUAL_EN.pdf",
        "https://www.feministinternet.com/",
        "https://craigwalker.com.au/",
        "https://onlineviolencewomen.eiu.com/",
        "https://webfoundation.org/2020/03/the-online-crisis-facing-women-and-girls-threatens-global-progress-on-gender-equality/",
        "https://webfoundation.org/2020/08/activists-and-tech-companies-met-to-talk-about-online-violence-against-women-here-are-the-takeaways/",
        "https://webfoundation.org/2020/08/activists-and-tech-companies-met-to-talk-about-online-violence-against-women-here-are-the-takeaways/",
        "https://webfoundation.org/2020/11/the-impact-of-online-gender-based-violence-on-women-in-public-life/",
        "https://webfoundation.org/2021/03/how-online-gender-based-violence-affects-the-safety-of-young-women-and-girls/",
        "https://webfoundation.org/2021/04/tech-policy-design-lab-pilot-building-solutions-to-tackle-online-abuse-of-women/",
        "https://ogbv.webfoundation.org/personas",
        "https://ogbv.webfoundation.org/prototypes#calm-the-crowd",
        "https://ogbv.webfoundation.org/prototypes#viral-notification",
        "https://ogbv.webfoundation.org/prototypes#reporting-20",
        "https://ogbv.webfoundation.org/prototypes#reporteroo",
        "https://ogbv.webfoundation.org/prototypes#gateway",
        "https://ogbv.webfoundation.org/prototypes#one-click",
        "https://ogbv.webfoundation.org/prototypes#calm-the-crowd",
        "https://ogbv.webfoundation.org/prototypes#image-shield",
        "https://ogbv.webfoundation.org/prototypes#wellbeing-check-up",
        "https://ogbv.webfoundation.org/prototypes#com-rod",
        "https://webfoundation.org/2020/11/the-impact-of-online-gender-based-violence-on-women-in-public-life/",
        "https://ogbv.webfoundation.org/prototypes#imatter",
        "https://ogbv.webfoundation.org/prototypes#reporteroo",
        "https://ogbv.webfoundation.org/prototypes#reporting-20",
        "https://ogbv.webfoundation.org/prototypes#image-shield",
        "https://ogbv.webfoundation.org/prototypes#gateway",
        "https://ogbv.webfoundation.org/prototypes#report-hub",
        "https://ogbv.webfoundation.org/prototypes#reporteroo",
        "https://ogbv.webfoundation.org",
        "https://webfoundation.org",
        "https://www.feministinternet.com",
        "https://craigwalker.com.au",
        "https://ogbv.webfoundation.org/resources#participants",
        "https://webfoundation.org",
        "https://www.feministinternet.com/",
        "https://craigwalker.com.au/",
        "https://outsight.international",
        "http://3x3.co",
        "http://conorrigby.com",
        "mailto:ogbv%40webfoundation.org?subject="
    ],
    "regex_uris": [],
    "regex_urls": [
        "http://www.w3.org/1999/02/22-rdf-syntax-ns#",
        "http://ns.adobe.com/xap/1.0/",
        "http://purl.org/dc/elements/1.1/",
        "http://ns.adobe.com/photoshop/1.0/",
        "http://ns.adobe.com/xap/1.0/mm/",
        "http://ns.adobe.com/xap/1.0/sType/ResourceEvent#",
        "http://www.w3.org/1999/02/22-rdf-syntax-ns#",
        "http://ns.adobe.com/xap/1.0/",
        "http://purl.org/dc/elements/1.1/",
        "http://ns.adobe.com/photoshop/1.0/",
        "http://ns.adobe.com/xap/1.0/mm/",
        "http://ns.adobe.com/xap/1.0/sType/ResourceEvent#",
        "http://www.w3.org/1999/02/22-rdf-syntax-ns#",
        "http://ns.adobe.com/xap/1.0/",
        "http://purl.org/dc/elements/1.1/",
        "http://ns.adobe.com/photoshop/1.0/",
        "http://ns.adobe.com/xap/1.0/mm/",
        "http://ns.adobe.com/xap/1.0/sType/ResourceEvent#",
        "https",
        "https",
        "www.feministinternet.com",
        "https",
        "http://www.w3.org/1999/02/22-rdf-syntax-ns#",
        "http://purl.org/dc/elements/1.1/",
        "http://www.w3.org/1999/02/22-rdf-syntax-ns#",
        "http://ns.adobe.com/xap/1.0/",
        "http://ns.adobe.com/xap/1.0/t/pg/",
        "http://ns.adobe.com/xap/1.0/sType/Dimensions#",
        "http://ns.adobe.com/xap/1.0/g/",
        "http://ns.adobe.com/illustrator/1.0/",
        "http://purl.org/dc/elements/1.1/",
        "http://ns.adobe.com/xap/1.0/mm/",
        "http://ns.adobe.com/pdf/1.3/",
        "http://www.w3.org/1999/02/22-rdf-syntax-ns#",
        "http://purl.org/dc/elements/1.1/",
        "https",
        "https",
        "www.feministinternet.com/",
        "https",
        "https",
        "https",
        "https",
        "https",
        "https",
        "https",
        "https",
        "https",
        "https",
        "https",
        "https",
        "https",
        "https",
        "https",
        "https",
        "https",
        "https",
        "https",
        "https",
        "https",
        "https",
        "https",
        "https",
        "https",
        "https",
        "https",
        "https",
        "https",
        "https",
        "https",
        "www.feministinternet.com",
        "https",
        "https",
        "www.feministinternet.com/",
        "http://3x3.co",
        "https",
        "https",
        "https",
        "https",
        "https",
        "http://conorrigby.com",
        "http://www.w3.org/1999/02/22-rdf-syntax-ns#",
        "http://ns.adobe.com/xap/1.0/",
        "http://ns.adobe.com/xap/1.0/mm/",
        "http://ns.adobe.com/xap/1.0/sType/ResourceRef#",
        "http://ns.adobe.com/xap/1.0/sType/ResourceEvent#",
        "http://purl.org/dc/elements/1.1/",
        "http://ns.adobe.com/pdf/1.3/"
    ],
    "scripts": {
        "iframe": [],
        "urls": []
    },
    "static_properties": {
        "JBIG2Decode": "0",
        "XML_forms": "0",
        "acro_form": "0",
        "auto_action": "0",
        "colors": "0",
        "cross_reference_table": "2",
        "embedded_files": "0",
        "file_size": "3.3",
        "java_script": "0",
        "js": "0",
        "launch_action": "0",
        "object_end": "514",
        "object_start": "514",
        "object_streams": "14",
        "open_action": "0",
        "page_count": "27",
        "rich_media": "0",
        "start_cross_reference_table": "2",
        "stream_end": "190",
        "stream_start": "190",
        "trailer_dictionary": "2"
    },
    "yara_signatures": []
}