{
    "exif_signatures": {},
    "file_size": 3839158,
    "pdfid_signatures": {},
    "pypdf_uris": [
        "http://picasaweb.google.com",
        "http://www.dlna.org",
        "https://www.google.com/accounts/ForgotPasswd",
        "https://www.google.com/accounts/ForgotPasswd",
        "http://market.android.com/support",
        "http://www.kobobooks.com/signup.html",
        "http://www.adobe.com/cfusion/membership/index.cfm",
        "http://www.adobe.com/cfusion/membership/index.cfm",
        "http://www.htc.com/support/",
        "http://www.htc.com/support/",
        "http://www.htcsense.com",
        "https://www.htcsense.com/"
    ],
    "regex_uris": [
        "http://picasaweb.google.com",
        "http://www.dlna.org",
        "https://www.google.com/accounts/ForgotPasswd",
        "https://www.google.com/accounts/ForgotPasswd",
        "http://market.android.com/support",
        "http://www.kobobooks.com/signup.html",
        "http://www.adobe.com/cfusion/membership/index.cfm",
        "http://www.adobe.com/cfusion/membership/index.cfm",
        "http://www.htc.com/support/",
        "http://www.htc.com/support/",
        "http://www.htcsense.com",
        "https://www.htcsense.com/"
    ],
    "regex_urls": [
        "http://picasaweb.google.com",
        "http://www.dlna.org",
        "https",
        "www.google.com/accounts/ForgotPasswd",
        "https",
        "www.google.com/accounts/ForgotPasswd",
        "http://market.android.com/support",
        "http://www.kobobooks.com/signup.html",
        "http://www.adobe.com/cfusion/membership/index.cfm",
        "http://www.adobe.com/cfusion/membership/index.cfm",
        "http://www.htc.com/support/",
        "http://www.htc.com/support/",
        "http://www.htcsense.com",
        "https",
        "www.htcsense.com/"
    ],
    "scripts": {
        "iframe": [],
        "urls": []
    },
    "static_properties": {
        "JBIG2Decode": "0",
        "XML_forms": "0",
        "acro_form": "0",
        "auto_action": "0",
        "colors": "0",
        "cross_reference_table": "1",
        "embedded_files": "0",
        "file_size": "3.8",
        "java_script": "0",
        "js": "0",
        "launch_action": "0",
        "object_end": "9890",
        "object_start": "9890",
        "object_streams": "0",
        "open_action": "0",
        "page_count": "203",
        "rich_media": "0",
        "start_cross_reference_table": "1",
        "stream_end": "722",
        "stream_start": "722",
        "trailer_dictionary": "1"
    },
    "yara_signatures": []
}